flexpipe/__init__.py
flexpipe/pipeline.py
flexpipe/tracker.py
flexpipe/transformation.py
flexpipe-2.2.0.dist-info/LICENSE
flexpipe-2.2.0.dist-info/METADATA
flexpipe-2.2.0.dist-info/WHEEL
flexpipe-2.2.0.dist-info/top_level.txt
flexpipe-2.2.0.dist-info/RECORD
