Metadata-Version: 2.1
Name: flexpipe
Version: 2.2.0
Summary: Flexible Pipeline Processing Framework
Author: Gaëtan Desrues
Classifier: Programming Language :: Python :: 3
Classifier: License :: OSI Approved :: MIT License
Classifier: Operating System :: OS Independent
License-File: LICENSE
Requires-Dist: python-gatools
Requires-Dist: pandas
